{
  "type": "object",
  "required": [
    "type",
    "groupKey",
    "tangles"
  ],
  "properties": {
    "type": {
      "type": "string",
      "pattern": "^group/init$"
    },
    "groupKey": {
      "$ref": "#/definitions/groupKey"
    },
    "tangles": {
      "type": "object",
      "required": [
        "group"
      ],
      "properties": {
        "group": {
          "$ref": "#/definitions/tangle/root"
        }
      }
    }
  },
  "additionalProperties": false,
  "definitions": {
    "groupKey": {
      "type": "string",
      "pattern": "^[a-zA-Z0-9\\/+]{42}[AEIMQUYcgkosw048]=$"
    },
    "tangle": {
      "root": {
        "type": "object",
        "required": [
          "root",
          "previous"
        ],
        "properties": {
          "root": {
            "type": "null"
          },
          "previous": {
            "type": "null"
          }
        }
      }
    }
  }
}